{
    "products": [
        {
            "_id": "product1",
            "image":"./images/product1.jpeg",
            "title": "Elegant Dress",
            "description": "elegant and sophisticated",
            "price": 39.99,
            "size": [8, 9, 10],
            "type": "dress"
        },
        {
            "_id": "product3",
            "image":"./images/product3.jpeg",
            "title": "Opens Stiletto",
            "description": "elegant and sophisticated",
            "price": 39.99,
            "size": [8, 9, 10],
            "type":"skirt"
        },
        {
            "_id": "product4",
            "image":"./images/product4.jpeg",
            "title": "Shiffon Jumsuite",
            "description": "elegant and sophisticated",
            "price": 69.99,
            "size": [8, 9, 10, 14, 16, 18],
            "type": "jumpsuite"

        },
        {
            "_id": "product5",
            "image":"./images/product5.jpeg",
            "title": "shiffon jumsuit",
            "description": "elegant and sophisticated",
            "price": 69.99,
            "size": [8, 9, 10, 14, 16, 18],
            "type": "dress"

        },
        {
            "_id": "product6",
            "image":"./images/product6.jpeg",
            "title": "shiffon jumsuit",
            "description": "elegant and sophisticated",
            "price": 69.99,
            "size": [8, 9, 10, 14, 16, 18],
            "type": "jumpsuite"

        },
        {
            "_id": "product7",
            "image":"./images/product7.jpeg",
            "title": "shiffon jumsuit",
            "description": "elegant and sophisticated",
            "price": 45.99,
            "size": [8, 9, 10, 14, 16, 18],
            "type": "jacket"

        },
        {
            "_id": "product8",
            "image":"./images/product8.jpeg",
            "title": "shiffon jumsuit",
            "description": "elegant and sophisticated",
            "price": 59.99,
            "size": [8, 9, 10, 14, 16, 18],
            "type": "jacket"

        }
    ]
}